async_mgun/__init__.py
async_mgun/mgun.py
async_mgun-0.1.3.dist-info/DESCRIPTION.rst
async_mgun-0.1.3.dist-info/METADATA
async_mgun-0.1.3.dist-info/RECORD
async_mgun-0.1.3.dist-info/WHEEL
async_mgun-0.1.3.dist-info/metadata.json
async_mgun-0.1.3.dist-info/top_level.txt
