Metadata-Version: 2.0
Name: async-mgun
Version: 0.1.3
Summary: HTTP REST Client based on aiohttp with dynamic url building
Home-page: https://github.com/maximdanilchenko/async-mgun
Author: Danilchenko Maksim
Author-email: dmax.dev@gmail.com
License: MIT
Keywords: http client rest aiohttp async request mgun
Platform: UNKNOWN
Classifier: Development Status :: 3 - Alpha
Classifier: Intended Audience :: Developers
Classifier: License :: OSI Approved :: MIT License
Classifier: Natural Language :: English
Classifier: Programming Language :: Python :: 3.5
Classifier: Programming Language :: Python :: 3.6
Requires-Dist: aiohttp
